gistPipeline/MainPipeline.py
gistPipeline/Mapviewer.py
gistPipeline/__init__.py
gistPipeline/_version.py
gistPipeline/auxiliary/__init__.py
gistPipeline/auxiliary/_auxiliary.py
gistPipeline/emissionLines/__init__.py
gistPipeline/emissionLines/_emissionLines.py
gistPipeline/emissionLines/gandalf.py
gistPipeline/emissionLines/pyGandalf/__init__.py
gistPipeline/emissionLines/pyGandalf/bvls_n.py
gistPipeline/emissionLines/pyGandalf/cap_mpfit.py
gistPipeline/emissionLines/pyGandalf/gandalf_util.py
gistPipeline/initialise/__init__.py
gistPipeline/initialise/_initialise.py
gistPipeline/lineStrengths/__init__.py
gistPipeline/lineStrengths/_lineStrengths.py
gistPipeline/lineStrengths/default.py
gistPipeline/lineStrengths/lsindex_spec.py
gistPipeline/lineStrengths/ssppop_fitting.py
gistPipeline/mapviewer/__init__.py
gistPipeline/mapviewer/createFigure.py
gistPipeline/mapviewer/createWindow.py
gistPipeline/mapviewer/helperFunctions.py
gistPipeline/mapviewer/loadData.py
gistPipeline/mapviewer/plotData.py
gistPipeline/plotting/__init__.py
gistPipeline/plotting/_plotting.py
gistPipeline/plotting/gistPlot_gas.py
gistPipeline/plotting/gistPlot_kin.py
gistPipeline/plotting/gistPlot_lambdar.py
gistPipeline/plotting/gistPlot_ls.py
gistPipeline/plotting/gistPlot_sfh.py
gistPipeline/prepareSpectra/__init__.py
gistPipeline/prepareSpectra/_prepareSpectra.py
gistPipeline/prepareSpectra/default.py
gistPipeline/prepareTemplates/__init__.py
gistPipeline/prepareTemplates/_prepareTemplates.py
gistPipeline/prepareTemplates/miles.py
gistPipeline/readData/CALIFA_V1200.py
gistPipeline/readData/CALIFA_V500.py
gistPipeline/readData/MUSE_NFM.py
gistPipeline/readData/MUSE_NFMAO.py
gistPipeline/readData/MUSE_WFM.py
gistPipeline/readData/MUSE_WFMAOE.py
gistPipeline/readData/MUSE_WFMAON.py
gistPipeline/readData/PLAINTXT.py
gistPipeline/readData/__init__.py
gistPipeline/readData/_readData.py
gistPipeline/readData/der_snr.py
gistPipeline/spatialBinning/__init__.py
gistPipeline-3.1.0.dist-info/LICENSE
gistPipeline-3.1.0.dist-info/METADATA
gistPipeline-3.1.0.dist-info/WHEEL
gistPipeline-3.1.0.dist-info/entry_points.txt
gistPipeline-3.1.0.dist-info/top_level.txt
gistPipeline-3.1.0.dist-info/RECORD
