Metadata-Version: 2.1
Name: gistPipeline
Version: 3.1.0
Summary: The GIST Framework: A multi-purpose tool for the analysis and visualisation of (integral-field) spectroscopic data
Home-page: https://abittner.gitlab.io/thegistpipeline/
Author: Adrian Bittner
Author-email: adrian.bittner@eso.org
License: Other/Proprietary License
Platform: UNKNOWN
Classifier: Intended Audience :: Science/Research
Classifier: Topic :: Scientific/Engineering :: Astronomy
Classifier: Programming Language :: Python :: 3
Classifier: Development Status :: 5 - Production/Stable
Classifier: License :: Other/Proprietary License
Requires-Python: ==3.6.*
License-File: LICENSE
Requires-Dist: astropy (>=3.1)
Requires-Dist: emcee (>=2.2)
Requires-Dist: matplotlib (>=3.1)
Requires-Dist: numpy (>=1.17)
Requires-Dist: PyQt5 (>=5.10)
Requires-Dist: scipy (>=1.3)
Requires-Dist: pyyaml (>=5.3)
Requires-Dist: vorbin (>=3.1)
Requires-Dist: ppxf (>=6.7)
Requires-Dist: plotbin (>=3.1)
Requires-Dist: printStatus (>=1.0)
